pygruenbeck_cloud/__init__.py
pygruenbeck_cloud/const.py
pygruenbeck_cloud/exceptions.py
pygruenbeck_cloud/models.py
pygruenbeck_cloud/py.typed
pygruenbeck_cloud/pygruenbeck_cloud.py
pygruenbeck_cloud-1.3.3.dist-info/licenses/LICENSE
requirements/production.txt
pygruenbeck_cloud-1.3.3.dist-info/METADATA
pygruenbeck_cloud-1.3.3.dist-info/WHEEL
pygruenbeck_cloud-1.3.3.dist-info/top_level.txt
pygruenbeck_cloud-1.3.3.dist-info/RECORD
