Metadata-Version: 2.4
Name: pygruenbeck_cloud
Version: 1.3.3
Summary: Python Library to communicate with Grünbeck Cloud based Water softeners
Author-email: Marco Neumann <pygruenbeck_cloud@binware.dev>
License: MIT License
Project-URL: Homepage, https://github.com/p0l0/pygruenbeck_cloud
Project-URL: Issues, https://github.com/p0l0/pygruenbeck_cloud/issues
Keywords: gruenbeck,gruenbeck-cloud,home,automation
Classifier: Development Status :: 5 - Production/Stable
Classifier: Intended Audience :: Developers
Classifier: License :: OSI Approved :: MIT License
Classifier: Operating System :: OS Independent
Classifier: Programming Language :: Python :: 3.12
Classifier: Programming Language :: Python :: 3.13
Classifier: Topic :: Home Automation
Requires-Python: >=3.12
License-File: LICENSE
Requires-Dist: aiohttp>=3.8.1
Requires-Dist: yarl>=1.9.4
Requires-Dist: dataclasses_json>=0.6.3
Dynamic: license-file
